stos/__init__.py
stos/base_classes.py
stos/metadata.py
stos/runtime.py
StosPy-0.1.dist-info/METADATA
StosPy-0.1.dist-info/WHEEL
StosPy-0.1.dist-info/top_level.txt
StosPy-0.1.dist-info/RECORD
